README.md
setup.py
pydomotic/__init__.py
pydomotic/__main__.py
pydomotic/actions.py
pydomotic/components.py
pydomotic/context.py
pydomotic/exceptions.py
pydomotic/handlers.py
pydomotic/lambda_handler.py
pydomotic/parsers.py
pydomotic/sensors.py
pydomotic/triggers.py
pydomotic/utils.py
pydomotic/version.py
pydomotic.egg-info/PKG-INFO
pydomotic.egg-info/SOURCES.txt
pydomotic.egg-info/dependency_links.txt
pydomotic.egg-info/requires.txt
pydomotic.egg-info/top_level.txt
pydomotic/providers/__init__.py
pydomotic/providers/airthings.py
pydomotic/providers/base.py
pydomotic/providers/ecobee.py
pydomotic/providers/fujitsu.py
pydomotic/providers/moen.py
pydomotic/providers/noop.py
pydomotic/providers/tuya.py