Metadata-Version: 2.1
Name: pydomotic
Version: 1.4.1
Summary: Python library for home automation execution, enabling seamless control and management of your IoT devices
Home-page: https://github.com/purple4reina/pydomotic
Author: Rey Abolofia
Author-email: purple4reina@gmail.com
License: MIT
Project-URL: Source, https://github.com/purple4reina/pydomotic
Project-URL: Bug Tracker, https://github.com/purple4reina/pydomotic/issues
Keywords: iot,python,home,automation,smart,domotic
Classifier: License :: OSI Approved :: MIT License
Classifier: Operating System :: OS Independent
Classifier: Topic :: Software Development
Classifier: Programming Language :: Python :: 3
Classifier: Programming Language :: Python :: 3.8
Classifier: Programming Language :: Python :: 3.9
Classifier: Programming Language :: Python :: 3.10
Classifier: Programming Language :: Python :: Implementation :: PyPy
Requires-Python: >=3.8,<4
Requires-Dist: PyYAML<7.0,>=6.0
Requires-Dist: astral<4.0,>=3.0
Requires-Dist: croniter<2.0,>=1.3.15
Requires-Dist: pyowm<4.0,>=3.3.0
Provides-Extra: airthings
Provides-Extra: ecobee
Provides-Extra: fujitsu
Requires-Dist: pyfujitsu<1.0,>=0.9.0; extra == "fujitsu"
Provides-Extra: moen
Requires-Dist: pyflowater<1.0,>=0.5.2; extra == "moen"
Requires-Dist: retry<1.0,>=0.9.2; extra == "moen"
Provides-Extra: tuya
Requires-Dist: gosundpy<1.0,>=0.7.0; extra == "tuya"
Provides-Extra: s3
Requires-Dist: boto3<2.0,>=1.26.3; extra == "s3"
Provides-Extra: tz
Requires-Dist: timezonefinder<7.0,>=6.1.8; extra == "tz"
Provides-Extra: all
Requires-Dist: pyfujitsu<1.0,>=0.9.0; extra == "all"
Requires-Dist: pyflowater<1.0,>=0.5.2; extra == "all"
Requires-Dist: retry<1.0,>=0.9.2; extra == "all"
Requires-Dist: gosundpy<1.0,>=0.7.0; extra == "all"
Requires-Dist: boto3<2.0,>=1.26.3; extra == "all"
Requires-Dist: timezonefinder<7.0,>=6.1.8; extra == "all"
